{
  "project_info": {
    "project_number": "526819218023",
    "firebase_url": "https://classroom-d0947-default-rtdb.firebaseio.com",
    "project_id": "classroom-d0947",
    "storage_bucket": "classroom-d0947.appspot.com"
  },
  "client": [
    {
      "client_info": {
        "mobilesdk_app_id": "1:526819218023:android:5cea65c3427f5042763ac2",
        "android_client_info": {
          "package_name": "com.example.classroom02"
        }
      },
      "oauth_client": [
        {
          "client_id": "526819218023-h328me0cq5j8ogei2cb0d35nbsl1r4is.apps.googleusercontent.com",
          "client_type": 1,
          "android_info": {
            "package_name": "com.example.classroom02",
            "certificate_hash": "13e7da527adccf0423f978c387169929a4342dab"
          }
        },
        {
          "client_id": "526819218023-sqfep03aki43ba2ho901i787kt2gmd1p.apps.googleusercontent.com",
          "client_type": 1,
          "android_info": {
            "package_name": "com.example.classroom02",
            "certificate_hash": "3a75bc059f1195c43fdae713ac479f37d4cdb527"
          }
        },
        {
          "client_id": "526819218023-ro8q1lmin9svv12c1eodmqcj5rtg74hq.apps.googleusercontent.com",
          "client_type": 3
        }
      ],
      "api_key": [
        {
          "current_key": "AIzaSyD-qMAHv1VoLM2GfeaXhN1IqzI45dXznK8"
        }
      ],
      "services": {
        "appinvite_service": {
          "other_platform_oauth_client": [
            {
              "client_id": "526819218023-5ll4ps0g6dmeabcnvt82ik3cc77c439g.apps.googleusercontent.com",
              "client_type": 3
            }
          ]
        }
      }
    },
    {
      "client_info": {
        "mobilesdk_app_id": "1:526819218023:android:8a77c82a5d9b2de7763ac2",
        "android_client_info": {
          "package_name": "com.example.quanlybantingiaovien"
        }
      },
      "oauth_client": [
        {
          "client_id": "526819218023-v044og83l0fbpdna6ba7ells47rl1kni.apps.googleusercontent.com",
          "client_type": 1,
          "android_info": {
            "package_name": "com.example.quanlybantingiaovien",
            "certificate_hash": "1cb759aa6a8f1e774db4e0824febd3aac59f2716"
          }
        },
        {
          "client_id": "526819218023-ro8q1lmin9svv12c1eodmqcj5rtg74hq.apps.googleusercontent.com",
          "client_type": 3
        }
      ],
      "api_key": [
        {
          "current_key": "AIzaSyD-qMAHv1VoLM2GfeaXhN1IqzI45dXznK8"
        }
      ],
      "services": {
        "appinvite_service": {
          "other_platform_oauth_client": [
            {
              "client_id": "526819218023-5ll4ps0g6dmeabcnvt82ik3cc77c439g.apps.googleusercontent.com",
              "client_type": 3
            }
          ]
        }
      }
    }
  ],
  "configuration_version": "1"
}